json_log_decorator/__init__.py
json_log_decorator/logdecorator.py
json_log_decorator-2.0.0.dist-info/LICENSE
json_log_decorator-2.0.0.dist-info/METADATA
json_log_decorator-2.0.0.dist-info/WHEEL
json_log_decorator-2.0.0.dist-info/top_level.txt
json_log_decorator-2.0.0.dist-info/RECORD
