Metadata-Version: 2.1
Name: json-log-decorator
Version: 2.0.0
Summary: The Python LogDecorator with exception, in JSON format
Home-page: https://github.com/rajeshkbathula/json_log_decorator
Author: Rajesh Bathula
Author-email: rajb2237@gmail.com
License: UNKNOWN
Platform: UNKNOWN
Classifier: Programming Language :: Python :: 3
Classifier: License :: OSI Approved :: MIT License
Classifier: Operating System :: OS Independent
Requires-Python: >=3.6
License-File: LICENSE
Requires-Dist: python-json-logger (==2.0.1)
Requires-Dist: python-logging-loki (==0.3.1)
